inverse_code/INVERSE_CODE.md
inverse_code/__init__.py
inverse_code/decode.py
inverse_code/encode.py
inverse_code/error.py
inverse_code/ascii/ASCII.md
inverse_code/ascii/__init__.py
inverse_code/ascii/asciitable.py
inverse_code/ascii/win1252.py
inverse_code/convert/CONVERT.md
inverse_code/convert/__init__.py
inverse_code/convert/cbin.py
inverse_code/convert/cdec.py
inverse_code/convert/chex.py
inverse_code/convert/coct.py
inverse_code/convert/csymb.py
inverse_code/helpers/HELPERS.md
inverse_code/helpers/__init__.py
inverse_code/helpers/binshow.py
inverse_code/helpers/decshow.py
inverse_code/helpers/helpers.py
inverse_code/helpers/hexshow.py
inverse_code/helpers/octshow.py
inverse_code/helpers/symbshow.py
inverse_code-1.2.dist-info/METADATA
inverse_code-1.2.dist-info/WHEEL
inverse_code-1.2.dist-info/entry_points.txt
inverse_code-1.2.dist-info/RECORD
