Metadata-Version: 2.4
Name: inverse_code
Version: 1.2
Summary: Reverse Code is a library created for Python to help developers encrypt and retrieve their data in a simple way.
Project-URL: Homepage, https://github.com/aniceto-jolela/inverse_code
Project-URL: Documentation, https://github.com/aniceto-jolela/inverse_code/blob/main/README.md
Project-URL: Repository, https://github.com/aniceto-jolela/inverse_code
Project-URL: Tests, https://github.com/aniceto-jolela/inverse_code/tree/main/tests
Project-URL: ASCII Reference, https://www.ascii-code.com/
Maintainer-email: Aniceto Jolela <otecina500@gmail.com>
License: MIT
Keywords: ascii,asciitable,bin,binary,code,convert,dec,decode,encode,helpers,hex,inverse-code,inverse_code,library,oct,pylintrc,readme,test,unittest,win1252,yield
Classifier: Development Status :: 5 - Production/Stable
Classifier: Intended Audience :: Developers
Classifier: License :: OSI Approved :: MIT License
Classifier: Operating System :: OS Independent
Classifier: Programming Language :: Python :: 3
Classifier: Programming Language :: Python :: 3.10
Classifier: Programming Language :: Python :: 3.11
Classifier: Programming Language :: Python :: 3.12
Classifier: Programming Language :: Python :: 3.13
Classifier: Topic :: Security :: Cryptography
Classifier: Topic :: Software Development :: Libraries :: Python Modules
Requires-Python: >=3.10
Requires-Dist: requests
Provides-Extra: dev
Requires-Dist: black>=23.7.0; extra == 'dev'
Requires-Dist: isort>=5.12.0; extra == 'dev'
Requires-Dist: pytest>=7.4.0; extra == 'dev'
Provides-Extra: pdf
Requires-Dist: reportlab>=1.2; extra == 'pdf'
Requires-Dist: rxp; extra == 'pdf'
Provides-Extra: rest
Requires-Dist: docutils>=0.3; extra == 'rest'
Requires-Dist: pack==1.1,==1.3; extra == 'rest'
